catabra_pandas/__init__.py
catabra_pandas/__version__.py
catabra_pandas/merging.py
catabra_pandas/misc.py
catabra_pandas/resampling.py
catabra_pandas-0.0.7.dist-info/LICENSE
catabra_pandas-0.0.7.dist-info/METADATA
catabra_pandas-0.0.7.dist-info/WHEEL
catabra_pandas-0.0.7.dist-info/RECORD
