Metadata-Version: 2.1
Name: catabra-pandas
Version: 0.0.7
Summary: CaTabRa-pandas is a library with additional functionality for pandas
Home-page: https://github.com/risc-mi/catabra-pandas
License: Apache 2.0 with Commons Clause
Author: RISC Software GmbH
Requires-Python: >=3.6.1,<4.0.0
Classifier: License :: Other/Proprietary License
Classifier: Programming Language :: Python :: 3
Classifier: Programming Language :: Python :: 3.7
Classifier: Programming Language :: Python :: 3.8
Classifier: Programming Language :: Python :: 3.9
Classifier: Programming Language :: Python :: 3.10
Classifier: Programming Language :: Python :: 3.11
Classifier: Programming Language :: Python :: 3.12
Requires-Dist: numpy (>=1.19.5) ; python_version < "3.9"
Requires-Dist: numpy (>=1.20.0) ; python_version >= "3.9"
Requires-Dist: pandas (>=1.0.0) ; python_version < "3.9"
Requires-Dist: pandas (>=1.1.0) ; python_version >= "3.9"
Project-URL: Repository, https://github.com/risc-mi/catabra-pandas
